awslabs/__init__.py
awslabs/aws_iot_sitewise_mcp_server/__init__.py
awslabs/aws_iot_sitewise_mcp_server/client.py
awslabs/aws_iot_sitewise_mcp_server/server.py
awslabs/aws_iot_sitewise_mcp_server/tool_metadata.py
awslabs/aws_iot_sitewise_mcp_server/validation.py
awslabs/aws_iot_sitewise_mcp_server/validation_utils.py
awslabs/aws_iot_sitewise_mcp_server/models/computation_data_models.py
awslabs/aws_iot_sitewise_mcp_server/models/metadata_transfer_data_models.py
awslabs/aws_iot_sitewise_mcp_server/prompts/__init__.py
awslabs/aws_iot_sitewise_mcp_server/prompts/anomaly_detection_workflow.py
awslabs/aws_iot_sitewise_mcp_server/prompts/asset_hierarchy.py
awslabs/aws_iot_sitewise_mcp_server/prompts/bulk_import_workflow.py
awslabs/aws_iot_sitewise_mcp_server/prompts/data_exploration.py
awslabs/aws_iot_sitewise_mcp_server/prompts/data_ingestion.py
awslabs/aws_iot_sitewise_mcp_server/tools/__init__.py
awslabs/aws_iot_sitewise_mcp_server/tools/sitewise_access.py
awslabs/aws_iot_sitewise_mcp_server/tools/sitewise_asset_models.py
awslabs/aws_iot_sitewise_mcp_server/tools/sitewise_assets.py
awslabs/aws_iot_sitewise_mcp_server/tools/sitewise_computation_models.py
awslabs/aws_iot_sitewise_mcp_server/tools/sitewise_data.py
awslabs/aws_iot_sitewise_mcp_server/tools/sitewise_executions.py
awslabs/aws_iot_sitewise_mcp_server/tools/sitewise_gateways.py
awslabs/aws_iot_sitewise_mcp_server/tools/sitewise_metadata_transfer.py
awslabs/aws_iot_sitewise_mcp_server/tools/timestamp_tools.py
awslabs_aws_iot_sitewise_mcp_server-11.0.10.dist-info/METADATA
awslabs_aws_iot_sitewise_mcp_server-11.0.10.dist-info/WHEEL
awslabs_aws_iot_sitewise_mcp_server-11.0.10.dist-info/entry_points.txt
awslabs_aws_iot_sitewise_mcp_server-11.0.10.dist-info/licenses/LICENSE
awslabs_aws_iot_sitewise_mcp_server-11.0.10.dist-info/licenses/NOTICE
awslabs_aws_iot_sitewise_mcp_server-11.0.10.dist-info/RECORD
